herbie/__init__.py
herbie/_version.py
herbie/accessors.py
herbie/cli.py
herbie/core.py
herbie/crs.py
herbie/fast.py
herbie/help.py
herbie/hrrr_zarr.py
herbie/latest.py
herbie/misc.py
herbie/nearest_points.py
herbie/pick_points.py
herbie/py.typed
herbie/show_versions.py
herbie/wgrib2.py
herbie/models/README.md
herbie/models/__init__.py
herbie/models/cfs.py
herbie/models/ecmwf.py
herbie/models/gdps.py
herbie/models/gefs.py
herbie/models/gfs.py
herbie/models/hafs.py
herbie/models/hiresw.py
herbie/models/hrdps.py
herbie/models/href.py
herbie/models/hrrr.py
herbie/models/local.py
herbie/models/nam.py
herbie/models/nbm.py
herbie/models/nexrad.py
herbie/models/rap.py
herbie/models/rdps.py
herbie/models/rrfs.py
herbie/models/rtma.py
herbie/models/urma.py
herbie/models/usnavy.py
herbie/paint/__init__.py
herbie/toolbox/__init__.py
herbie/toolbox/cartopy_scalebar.py
herbie/toolbox/cartopy_tools.py
herbie/toolbox/pressure.py
herbie/toolbox/units.py
herbie/toolbox/wind.py
herbie_data-2025.11.2.dist-info/METADATA
herbie_data-2025.11.2.dist-info/WHEEL
herbie_data-2025.11.2.dist-info/entry_points.txt
herbie_data-2025.11.2.dist-info/licenses/LICENSE
herbie_data-2025.11.2.dist-info/RECORD
