Metadata-Version: 2.4
Name: herbie-data
Version: 2025.11.2
Summary: Download numerical weather prediction GRIB2 model data.
Project-URL: Homepage, https://github.com/blaylockbk/Herbie
Project-URL: Documentation, https://herbie.readthedocs.io/
Project-URL: Repository, https://github.com/blaylockbk/Herbie
Project-URL: Changelog, https://github.com/blaylockbk/Herbie/releases
Project-URL: Bug Tracker, https://github.com/blaylockbk/Herbie/issues
Author-email: "Brian K. Blaylock" <blaylockbk@gmail.com>
Maintainer-email: "Brian K. Blaylock" <blaylockbk@gmail.com>
License: MIT License
License-File: LICENSE
Keywords: GRIB2,HRRR,atmosphere,forecast,meteorology,weather,xarray
Classifier: Development Status :: 4 - Beta
Classifier: Intended Audience :: Science/Research
Classifier: License :: OSI Approved :: MIT License
Classifier: Operating System :: MacOS
Classifier: Operating System :: Microsoft :: Windows
Classifier: Operating System :: POSIX :: Linux
Classifier: Programming Language :: Python :: 3
Classifier: Programming Language :: Python :: 3.10
Classifier: Programming Language :: Python :: 3.11
Classifier: Programming Language :: Python :: 3.12
Classifier: Programming Language :: Python :: 3.13
Classifier: Topic :: Scientific/Engineering :: Atmospheric Science
Requires-Python: >=3.10
Requires-Dist: cfgrib>=0.9.15
Requires-Dist: eccodes>=2.37.0
Requires-Dist: numpy>=1.24
Requires-Dist: pandas>=2.1
Requires-Dist: pyproj>=3.7.0
Requires-Dist: requests>=2.23.3
Requires-Dist: toml>=0.10.2
Requires-Dist: xarray>=2025.1.1
Provides-Extra: extras
Requires-Dist: cartopy; extra == 'extras'
Requires-Dist: matplotlib; extra == 'extras'
Requires-Dist: metpy; extra == 'extras'
Requires-Dist: scikit-learn; extra == 'extras'
Provides-Extra: metpy
Requires-Dist: metpy; extra == 'metpy'
Provides-Extra: plot
Requires-Dist: cartopy; extra == 'plot'
Requires-Dist: matplotlib; extra == 'plot'
Requires-Dist: metpy; extra == 'plot'
Provides-Extra: pygrib
Requires-Dist: pygrib; extra == 'pygrib'
Provides-Extra: scikit-learn
Requires-Dist: scikit-learn; extra == 'scikit-learn'
